minchin/django/excel/__init__.py
minchin/django/excel/admin.py
minchin/django/excel/apps.py
minchin/django/excel/models.py
minchin/django/excel/tests.py
minchin/django/excel/urls.py
minchin/django/excel/utils.py
minchin/django/excel/views.py
minchin/django/excel/management/commands/jsonize_rows.py
minchin/django/excel/management/commands/load_excel.py
minchin/django/excel/migrations/0001_initial.py
minchin/django/excel/migrations/__init__.py
minchin/django/excel/templates/admin/edit_inline/tabular_paginated.html
minchin/django/excel/templatetags/__init__.py
minchin/django/excel/templatetags/excel_tags.py
minchin_django_excel-1.0.0.dist-info/licenses/LICENSE.txt
minchin_django_excel-1.0.0.dist-info/METADATA
minchin_django_excel-1.0.0.dist-info/WHEEL
minchin_django_excel-1.0.0.dist-info/top_level.txt
minchin_django_excel-1.0.0.dist-info/RECORD
