Metadata-Version: 2.4
Name: minchin.django.excel
Version: 1.0.0
Summary: Load Excel files into your Django database.
Author-email: William Minchin <w_minchin@hotmail.com>
Maintainer-email: William Minchin <w_minchin@hotmail.com>
License-Expression: MIT
Project-URL: Repository, https://github.com/minchinweb/minchin.django.excel
Classifier: Development Status :: 5 - Production/Stable
Classifier: Environment :: Web Environment
Classifier: Intended Audience :: Developers
Classifier: Operating System :: OS Independent
Classifier: Programming Language :: Python :: 3 :: Only
Classifier: Topic :: Software Development :: Libraries :: Python Modules
Classifier: Framework :: Django
License-File: LICENSE.txt
Requires-Dist: django>=4.0
Requires-Dist: django-auto-prefetch>=0.0.6
Requires-Dist: ciso8601>=2.2.0
Requires-Dist: dateparser>=1.1.1
Requires-Dist: numpy>=1.22.4
Requires-Dist: pytz>=2022.1
Requires-Dist: psycopg2>=2.9.3
Requires-Dist: pandas>=1.4.2
Requires-Dist: colorama>=0.4.4
Requires-Dist: minchin.text>=6.1.0
Requires-Dist: django-prettyjson>=0.4.1
Requires-Dist: django-related-admin==1.0.1
Requires-Dist: openpyxl>=3.0.10
Provides-Extra: dev
Requires-Dist: invoke; extra == "dev"
Requires-Dist: minchin.releaser; extra == "dev"
Requires-Dist: isort; extra == "dev"
Requires-Dist: black; extra == "dev"
Dynamic: license-file
